[{"funcao":"10 - Saúde","subFuncao":"306 - Alimentação E Nutrição","ano":"2012","valor":57325.75},{"funcao":"10 - Saúde","subFuncao":"306 - Alimentação E Nutrição","ano":"2013","valor":46675.78},{"funcao":"10 - Saúde","subFuncao":"306 - Alimentação E Nutrição","ano":"2014","valor":74081.31},{"funcao":"10 - Saúde","subFuncao":"305 - Vigilância Epidemiológica","ano":"2012","valor":292150.68},{"funcao":"10 - Saúde","subFuncao":"305 - Vigilância Epidemiológica","ano":"2013","valor":354004.78},{"funcao":"10 - Saúde","subFuncao":"305 - Vigilância Epidemiológica","ano":"2014","valor":286932.03},{"funcao":"10 - Saúde","subFuncao":"304 - Vigilância Sanitária","ano":"2012","valor":911474.18},{"funcao":"10 - Saúde","subFuncao":"304 - Vigilância Sanitária","ano":"2013","valor":1060952.14},{"funcao":"10 - Saúde","subFuncao":"304 - Vigilância Sanitária","ano":"2014","valor":571739.14},{"funcao":"10 - Saúde","subFuncao":"302 - Assistência Hospitalar E Ambulatorial","ano":"2012","valor":38340.84},{"funcao":"10 - Saúde","subFuncao":"302 - Assistência Hospitalar E Ambulatorial","ano":"2013","valor":795767.98},{"funcao":"10 - Saúde","subFuncao":"302 - Assistência Hospitalar E Ambulatorial","ano":"2014","valor":2260197.47},{"funcao":"10 - Saúde","subFuncao":"301 - Atenção Básica","ano":"2012","valor":6233547.57},{"funcao":"10 - Saúde","subFuncao":"301 - Atenção Básica","ano":"2013","valor":7517394.33},{"funcao":"10 - Saúde","subFuncao":"301 - Atenção Básica","ano":"2014","valor":9810195.06},{"funcao":"08 - Assistência Social","subFuncao":"244 - Assistência Comunitária","ano":"2012","valor":780867.26},{"funcao":"08 - Assistência Social","subFuncao":"244 - Assistência Comunitária","ano":"2013","valor":726783.28},{"funcao":"08 - Assistência Social","subFuncao":"244 - Assistência Comunitária","ano":"2014","valor":658133.56},{"funcao":"08 - Assistência Social","subFuncao":"243 - Assistência À Criança E Ao Adoslescente","ano":"2012","valor":243710.46},{"funcao":"08 - Assistência Social","subFuncao":"243 - Assistência À Criança E Ao Adoslescente","ano":"2013","valor":236450.18},{"funcao":"08 - Assistência Social","subFuncao":"243 - Assistência À Criança E Ao Adoslescente","ano":"2014","valor":281295.07},{"funcao":"08 - Assistência Social","subFuncao":"241 - Assistência Ao Idoso","ano":"2012","valor":102306.63},{"funcao":"08 - Assistência Social","subFuncao":"241 - Assistência Ao Idoso","ano":"2013","valor":102640.51},{"funcao":"08 - Assistência Social","subFuncao":"241 - Assistência Ao Idoso","ano":"2014","valor":357642.75},{"funcao":"06 - Segurança Pública","subFuncao":"181 - Policiamento","ano":"2012","valor":69992.47},{"funcao":"06 - Segurança Pública","subFuncao":"181 - Policiamento","ano":"2013","valor":17220.51},{"funcao":"06 - Segurança Pública","subFuncao":"181 - Policiamento","ano":"2014","valor":17505.96},{"funcao":"04 - Administração","subFuncao":"122 - Administração Geral","ano":"2012","valor":4524623.69},{"funcao":"04 - Administração","subFuncao":"122 - Administração Geral","ano":"2013","valor":4985191.96},{"funcao":"04 - Administração","subFuncao":"122 - Administração Geral","ano":"2014","valor":6007129.52},{"funcao":"01 - Legislativa","subFuncao":"031 - Ação Legislativa","ano":"2012","valor":844939.46},{"funcao":"01 - Legislativa","subFuncao":"031 - Ação Legislativa","ano":"2013","valor":885480.88},{"funcao":"01 - Legislativa","subFuncao":"031 - Ação Legislativa","ano":"2014","valor":902364.74},{"funcao":"12 - Educação","subFuncao":"364 - Ensino Superior","ano":"2012","valor":8797.5},{"funcao":"12 - Educação","subFuncao":"364 - Ensino Superior","ano":"2013","valor":175},{"funcao":"12 - Educação","subFuncao":"364 - Ensino Superior","ano":"2014","valor":23738},{"funcao":"12 - Educação","subFuncao":"365 - Educação Infantil","ano":"2012","valor":3680945.61},{"funcao":"12 - Educação","subFuncao":"365 - Educação Infantil","ano":"2013","valor":2996877.51},{"funcao":"12 - Educação","subFuncao":"365 - Educação Infantil","ano":"2014","valor":5134857.61},{"funcao":"13 - Cultura","subFuncao":"126 - Tecnologia Da Informatização","ano":"2012","valor":21155.64},{"funcao":"13 - Cultura","subFuncao":"126 - Tecnologia Da Informatização","ano":"2013","valor":12457.7},{"funcao":"13 - Cultura","subFuncao":"126 - Tecnologia Da Informatização","ano":"2014","valor":27506.45},{"funcao":"13 - Cultura","subFuncao":"392 - Difusão Cultural","ano":"2012","valor":861183.01},{"funcao":"13 - Cultura","subFuncao":"392 - Difusão Cultural","ano":"2013","valor":1396653.13},{"funcao":"13 - Cultura","subFuncao":"392 - Difusão Cultural","ano":"2014","valor":2158490.99},{"funcao":"15 - Urbanismo","subFuncao":"452 - Serviços Urbanos","ano":"2012","valor":3623392.53},{"funcao":"15 - Urbanismo","subFuncao":"452 - Serviços Urbanos","ano":"2013","valor":2913297.61},{"funcao":"15 - Urbanismo","subFuncao":"452 - Serviços Urbanos","ano":"2014","valor":3836787.67},{"funcao":"15 - Urbanismo","subFuncao":"453 - Transportes Coletivos Urbanos","ano":"2014","valor":217642.87},{"funcao":"22 - Indústria","subFuncao":"661 - Promoção Industrial","ano":"2014","valor":178988.03},{"funcao":"23 - Comércio E Serviços","subFuncao":"694 - Serviços Financeiros","ano":"2012","valor":23784.3},{"funcao":"23 - Comércio E Serviços","subFuncao":"694 - Serviços Financeiros","ano":"2013","valor":5659.4},{"funcao":"23 - Comércio E Serviços","subFuncao":"694 - Serviços Financeiros","ano":"2014","valor":63099.14},{"funcao":"17 - Saneamento","subFuncao":"122 - Administração Geral","ano":"2014","valor":70609.16},{"funcao":"17 - Saneamento","subFuncao":"512 - Saneamento Básico Urbano","ano":"2012","valor":1951909.98},{"funcao":"17 - Saneamento","subFuncao":"512 - Saneamento Básico Urbano","ano":"2013","valor":1334101.42},{"funcao":"17 - Saneamento","subFuncao":"512 - Saneamento Básico Urbano","ano":"2014","valor":1455256.39},{"funcao":"20 - Agricultura","subFuncao":"601 - Promoçào Da Produção Vegetal","ano":"2012","valor":154731.33},{"funcao":"20 - Agricultura","subFuncao":"601 - Promoçào Da Produção Vegetal","ano":"2013","valor":75834.92},{"funcao":"20 - Agricultura","subFuncao":"601 - Promoçào Da Produção Vegetal","ano":"2014","valor":42485.89},{"funcao":"28 - Encargos Especiais","subFuncao":"846 - Outros Encargos Especiais","ano":"2012","valor":771196.49},{"funcao":"28 - Encargos Especiais","subFuncao":"846 - Outros Encargos Especiais","ano":"2013","valor":638769.33},{"funcao":"28 - Encargos Especiais","subFuncao":"846 - Outros Encargos Especiais","ano":"2014","valor":714361.94},{"funcao":"27 - Desporto E Lazer","subFuncao":"811 - Desporto De Rendimento","ano":"2012","valor":488961.61},{"funcao":"27 - Desporto E Lazer","subFuncao":"811 - Desporto De Rendimento","ano":"2013","valor":592004.33},{"funcao":"27 - Desporto E Lazer","subFuncao":"811 - Desporto De Rendimento","ano":"2014","valor":679835.59},{"funcao":"26 - Transporte","subFuncao":"782 - Transporte Rodoviário","ano":"2012","valor":2567175.7},{"funcao":"26 - Transporte","subFuncao":"782 - Transporte Rodoviário","ano":"2013","valor":2630695.63},{"funcao":"26 - Transporte","subFuncao":"782 - Transporte Rodoviário","ano":"2014","valor":2115875.2},{"funcao":"24 - Comunicações","subFuncao":"722 - Telecomunicações","ano":"2012","valor":68571.47},{"funcao":"24 - Comunicações","subFuncao":"722 - Telecomunicações","ano":"2013","valor":58289.58},{"funcao":"24 - Comunicações","subFuncao":"722 - Telecomunicações","ano":"2014","valor":63300.7},{"funcao":"28 - Encargos Especiais","subFuncao":"843 - Serviço Da Dívida Interna","ano":"2012","valor":1252841.37},{"funcao":"28 - Encargos Especiais","subFuncao":"843 - Serviço Da Dívida Interna","ano":"2013","valor":1341909.39},{"funcao":"28 - Encargos Especiais","subFuncao":"843 - Serviço Da Dívida Interna","ano":"2014","valor":1397263.11},{"funcao":"12 - Educação","subFuncao":"362 - Ensino Médio","ano":"2012","valor":197431.86},{"funcao":"12 - Educação","subFuncao":"362 - Ensino Médio","ano":"2013","valor":337112.88},{"funcao":"12 - Educação","subFuncao":"362 - Ensino Médio","ano":"2014","valor":336857.94},{"funcao":"12 - Educação","subFuncao":"361 - Ensino Fundamental","ano":"2012","valor":4328798.69},{"funcao":"12 - Educação","subFuncao":"361 - Ensino Fundamental","ano":"2013","valor":5772436.7},{"funcao":"12 - Educação","subFuncao":"361 - Ensino Fundamental","ano":"2014","valor":7052718.23}]