[{"funcao":"06 - Segurança Pública","subFuncao":"182 - Defesa Civil","ano":"2014","valor":57860},{"funcao":"08 - Assistência Social","subFuncao":"241 - Assistência Ao Idoso","ano":"2012","valor":102829.6},{"funcao":"08 - Assistência Social","subFuncao":"241 - Assistência Ao Idoso","ano":"2014","valor":248772.8},{"funcao":"08 - Assistência Social","subFuncao":"243 - Assistência À Criança E Ao Adoslescente","ano":"2012","valor":64462.46},{"funcao":"08 - Assistência Social","subFuncao":"243 - Assistência À Criança E Ao Adoslescente","ano":"2013","valor":67166.88},{"funcao":"08 - Assistência Social","subFuncao":"243 - Assistência À Criança E Ao Adoslescente","ano":"2014","valor":82176.4},{"funcao":"08 - Assistência Social","subFuncao":"244 - Assistência Comunitária","ano":"2012","valor":640328.25},{"funcao":"08 - Assistência Social","subFuncao":"244 - Assistência Comunitária","ano":"2013","valor":552924.15},{"funcao":"08 - Assistência Social","subFuncao":"244 - Assistência Comunitária","ano":"2014","valor":982241.61},{"funcao":"09 - Previdência Social","subFuncao":"271 - Previdência Básica","ano":"2012","valor":455322.68},{"funcao":"09 - Previdência Social","subFuncao":"271 - Previdência Básica","ano":"2013","valor":452856.39},{"funcao":"09 - Previdência Social","subFuncao":"271 - Previdência Básica","ano":"2014","valor":452573.62},{"funcao":"10 - Saúde","subFuncao":"301 - Atenção Básica","ano":"2012","valor":4509838.61},{"funcao":"10 - Saúde","subFuncao":"301 - Atenção Básica","ano":"2013","valor":5576478.99},{"funcao":"10 - Saúde","subFuncao":"301 - Atenção Básica","ano":"2014","valor":7443060.73},{"funcao":"28 - Encargos Especiais","subFuncao":"846 - Outros Encargos Especiais","ano":"2012","valor":328822.02},{"funcao":"28 - Encargos Especiais","subFuncao":"846 - Outros Encargos Especiais","ano":"2013","valor":319267.97},{"funcao":"28 - Encargos Especiais","subFuncao":"846 - Outros Encargos Especiais","ano":"2014","valor":362250.45},{"funcao":"28 - Encargos Especiais","subFuncao":"843 - Serviço Da Dívida Interna","ano":"2012","valor":197556.33},{"funcao":"28 - Encargos Especiais","subFuncao":"843 - Serviço Da Dívida Interna","ano":"2013","valor":120342.26},{"funcao":"28 - Encargos Especiais","subFuncao":"843 - Serviço Da Dívida Interna","ano":"2014","valor":202931.93},{"funcao":"27 - Desporto E Lazer","subFuncao":"813 - Lazer","ano":"2012","valor":2500},{"funcao":"27 - Desporto E Lazer","subFuncao":"813 - Lazer","ano":"2014","valor":23942.95},{"funcao":"27 - Desporto E Lazer","subFuncao":"811 - Desporto De Rendimento","ano":"2012","valor":541509.06},{"funcao":"27 - Desporto E Lazer","subFuncao":"811 - Desporto De Rendimento","ano":"2013","valor":186887.14},{"funcao":"27 - Desporto E Lazer","subFuncao":"811 - Desporto De Rendimento","ano":"2014","valor":261199.8},{"funcao":"26 - Transporte","subFuncao":"782 - Transporte Rodoviário","ano":"2012","valor":240256.42},{"funcao":"26 - Transporte","subFuncao":"782 - Transporte Rodoviário","ano":"2013","valor":305211.08},{"funcao":"26 - Transporte","subFuncao":"782 - Transporte Rodoviário","ano":"2014","valor":276939.36},{"funcao":"23 - Comércio E Serviços","subFuncao":"695 - Turismo","ano":"2012","valor":760387.03},{"funcao":"23 - Comércio E Serviços","subFuncao":"695 - Turismo","ano":"2013","valor":793604.52},{"funcao":"23 - Comércio E Serviços","subFuncao":"695 - Turismo","ano":"2014","valor":876779.26},{"funcao":"20 - Agricultura","subFuncao":"605 - Abastecimento","ano":"2012","valor":115730.77},{"funcao":"20 - Agricultura","subFuncao":"605 - Abastecimento","ano":"2013","valor":63689.04},{"funcao":"20 - Agricultura","subFuncao":"605 - Abastecimento","ano":"2014","valor":285720.91},{"funcao":"20 - Agricultura","subFuncao":"602 - Promoçào Da Produção Animal","ano":"2012","valor":3170},{"funcao":"20 - Agricultura","subFuncao":"602 - Promoçào Da Produção Animal","ano":"2014","valor":9830.23},{"funcao":"20 - Agricultura","subFuncao":"601 - Promoçào Da Produção Vegetal","ano":"2013","valor":17990},{"funcao":"18 - Gestão Ambiental","subFuncao":"541 - Preservação E Conservação Ambiental","ano":"2014","valor":85},{"funcao":"17 - Saneamento","subFuncao":"512 - Saneamento Básico Urbano","ano":"2012","valor":756208.12},{"funcao":"17 - Saneamento","subFuncao":"512 - Saneamento Básico Urbano","ano":"2013","valor":735275.85},{"funcao":"17 - Saneamento","subFuncao":"512 - Saneamento Básico Urbano","ano":"2014","valor":531665.37},{"funcao":"16 - Habitação","subFuncao":"482 - Habitação Urbana","ano":"2014","valor":58500},{"funcao":"15 - Urbanismo","subFuncao":"452 - Serviços Urbanos","ano":"2012","valor":1797661.75},{"funcao":"15 - Urbanismo","subFuncao":"452 - Serviços Urbanos","ano":"2013","valor":2265710.96},{"funcao":"15 - Urbanismo","subFuncao":"452 - Serviços Urbanos","ano":"2014","valor":2385829.01},{"funcao":"15 - Urbanismo","subFuncao":"451 - Infra-Estrutura Urbana","ano":"2012","valor":4075512.7},{"funcao":"15 - Urbanismo","subFuncao":"451 - Infra-Estrutura Urbana","ano":"2013","valor":2022335.11},{"funcao":"15 - Urbanismo","subFuncao":"451 - Infra-Estrutura Urbana","ano":"2014","valor":2868815.73},{"funcao":"13 - Cultura","subFuncao":"392 - Difusão Cultural","ano":"2012","valor":659322.07},{"funcao":"13 - Cultura","subFuncao":"392 - Difusão Cultural","ano":"2013","valor":709982.86},{"funcao":"13 - Cultura","subFuncao":"392 - Difusão Cultural","ano":"2014","valor":788170.25},{"funcao":"12 - Educação","subFuncao":"367 - Educação Especial","ano":"2012","valor":23950},{"funcao":"12 - Educação","subFuncao":"367 - Educação Especial","ano":"2013","valor":29270},{"funcao":"12 - Educação","subFuncao":"367 - Educação Especial","ano":"2014","valor":53040},{"funcao":"12 - Educação","subFuncao":"366 - Educação De Jovens E Adultos","ano":"2013","valor":81249.65},{"funcao":"12 - Educação","subFuncao":"366 - Educação De Jovens E Adultos","ano":"2014","valor":185039.03},{"funcao":"12 - Educação","subFuncao":"365 - Educação Infantil","ano":"2012","valor":1447888.92},{"funcao":"12 - Educação","subFuncao":"365 - Educação Infantil","ano":"2013","valor":1406286.09},{"funcao":"12 - Educação","subFuncao":"365 - Educação Infantil","ano":"2014","valor":2142202.71},{"funcao":"12 - Educação","subFuncao":"364 - Ensino Superior","ano":"2012","valor":16384},{"funcao":"12 - Educação","subFuncao":"364 - Ensino Superior","ano":"2013","valor":9753},{"funcao":"12 - Educação","subFuncao":"364 - Ensino Superior","ano":"2014","valor":4208},{"funcao":"12 - Educação","subFuncao":"363 - Ensino Profissional","ano":"2012","valor":7267.77},{"funcao":"12 - Educação","subFuncao":"363 - Ensino Profissional","ano":"2013","valor":14495.45},{"funcao":"12 - Educação","subFuncao":"363 - Ensino Profissional","ano":"2014","valor":8263.36},{"funcao":"12 - Educação","subFuncao":"362 - Ensino Médio","ano":"2012","valor":243638.17},{"funcao":"12 - Educação","subFuncao":"362 - Ensino Médio","ano":"2013","valor":254400.64},{"funcao":"12 - Educação","subFuncao":"362 - Ensino Médio","ano":"2014","valor":223387.48},{"funcao":"12 - Educação","subFuncao":"361 - Ensino Fundamental","ano":"2012","valor":6348532.66},{"funcao":"12 - Educação","subFuncao":"361 - Ensino Fundamental","ano":"2013","valor":7335696.89},{"funcao":"12 - Educação","subFuncao":"361 - Ensino Fundamental","ano":"2014","valor":7291565.85},{"funcao":"12 - Educação","subFuncao":"306 - Alimentação E Nutrição","ano":"2012","valor":438013.18},{"funcao":"12 - Educação","subFuncao":"306 - Alimentação E Nutrição","ano":"2013","valor":419887.96},{"funcao":"12 - Educação","subFuncao":"306 - Alimentação E Nutrição","ano":"2014","valor":624119.38},{"funcao":"10 - Saúde","subFuncao":"305 - Vigilância Epidemiológica","ano":"2012","valor":166270.05},{"funcao":"10 - Saúde","subFuncao":"305 - Vigilância Epidemiológica","ano":"2013","valor":42924.83},{"funcao":"10 - Saúde","subFuncao":"305 - Vigilância Epidemiológica","ano":"2014","valor":188825.05},{"funcao":"10 - Saúde","subFuncao":"304 - Vigilância Sanitária","ano":"2012","valor":139919.4},{"funcao":"10 - Saúde","subFuncao":"304 - Vigilância Sanitária","ano":"2013","valor":119986.26},{"funcao":"10 - Saúde","subFuncao":"304 - Vigilância Sanitária","ano":"2014","valor":69081.21},{"funcao":"10 - Saúde","subFuncao":"302 - Assistência Hospitalar E Ambulatorial","ano":"2012","valor":100242.86},{"funcao":"10 - Saúde","subFuncao":"302 - Assistência Hospitalar E Ambulatorial","ano":"2013","valor":568283.44},{"funcao":"10 - Saúde","subFuncao":"302 - Assistência Hospitalar E Ambulatorial","ano":"2014","valor":859466.96},{"funcao":"01 - Legislativa","subFuncao":"031 - Ação Legislativa","ano":"2012","valor":547287.55},{"funcao":"01 - Legislativa","subFuncao":"031 - Ação Legislativa","ano":"2013","valor":570267.62},{"funcao":"01 - Legislativa","subFuncao":"031 - Ação Legislativa","ano":"2014","valor":604835.94},{"funcao":"04 - Administração","subFuncao":"122 - Administração Geral","ano":"2012","valor":2540198.24},{"funcao":"04 - Administração","subFuncao":"122 - Administração Geral","ano":"2013","valor":2490983.59},{"funcao":"04 - Administração","subFuncao":"122 - Administração Geral","ano":"2014","valor":2735064.26},{"funcao":"04 - Administração","subFuncao":"123 - Administração Financeira","ano":"2012","valor":1593895.92},{"funcao":"04 - Administração","subFuncao":"123 - Administração Financeira","ano":"2013","valor":1592725.41},{"funcao":"04 - Administração","subFuncao":"123 - Administração Financeira","ano":"2014","valor":1653764.19}]