[{"funcao":"08 - Assistência Social","subFuncao":"243 - Assistência À Criança E Ao Adoslescente","ano":"2012","valor":304236.13},{"funcao":"08 - Assistência Social","subFuncao":"243 - Assistência À Criança E Ao Adoslescente","ano":"2013","valor":403555.63},{"funcao":"08 - Assistência Social","subFuncao":"243 - Assistência À Criança E Ao Adoslescente","ano":"2014","valor":325204.76},{"funcao":"08 - Assistência Social","subFuncao":"244 - Assistência Comunitária","ano":"2012","valor":2852245.24},{"funcao":"08 - Assistência Social","subFuncao":"244 - Assistência Comunitária","ano":"2013","valor":3103617.69},{"funcao":"08 - Assistência Social","subFuncao":"244 - Assistência Comunitária","ano":"2014","valor":3030201.77},{"funcao":"09 - Previdência Social","subFuncao":"272 - Previdência Do Regime Estatutário","ano":"2012","valor":718762.54},{"funcao":"09 - Previdência Social","subFuncao":"272 - Previdência Do Regime Estatutário","ano":"2013","valor":738338.97},{"funcao":"09 - Previdência Social","subFuncao":"272 - Previdência Do Regime Estatutário","ano":"2014","valor":748326.9},{"funcao":"10 - Saúde","subFuncao":"301 - Atenção Básica","ano":"2012","valor":10831858.92},{"funcao":"10 - Saúde","subFuncao":"301 - Atenção Básica","ano":"2013","valor":12692837.72},{"funcao":"10 - Saúde","subFuncao":"301 - Atenção Básica","ano":"2014","valor":15847384.46},{"funcao":"10 - Saúde","subFuncao":"303 - Suporte Profilático E Terapêutico","ano":"2012","valor":1151047.04},{"funcao":"10 - Saúde","subFuncao":"303 - Suporte Profilático E Terapêutico","ano":"2013","valor":1272650.65},{"funcao":"10 - Saúde","subFuncao":"303 - Suporte Profilático E Terapêutico","ano":"2014","valor":1284150.9},{"funcao":"10 - Saúde","subFuncao":"304 - Vigilância Sanitária","ano":"2012","valor":3019.33},{"funcao":"10 - Saúde","subFuncao":"304 - Vigilância Sanitária","ano":"2013","valor":6574.7},{"funcao":"10 - Saúde","subFuncao":"304 - Vigilância Sanitária","ano":"2014","valor":6084.14},{"funcao":"10 - Saúde","subFuncao":"305 - Vigilância Epidemiológica","ano":"2012","valor":167722.89},{"funcao":"10 - Saúde","subFuncao":"305 - Vigilância Epidemiológica","ano":"2013","valor":196438.91},{"funcao":"10 - Saúde","subFuncao":"305 - Vigilância Epidemiológica","ano":"2014","valor":185443.2},{"funcao":"10 - Saúde","subFuncao":"306 - Alimentação E Nutrição","ano":"2012","valor":39948.12},{"funcao":"10 - Saúde","subFuncao":"306 - Alimentação E Nutrição","ano":"2013","valor":62259.04},{"funcao":"10 - Saúde","subFuncao":"306 - Alimentação E Nutrição","ano":"2014","valor":36601.7},{"funcao":"12 - Educação","subFuncao":"306 - Alimentação E Nutrição","ano":"2012","valor":677468.65},{"funcao":"12 - Educação","subFuncao":"306 - Alimentação E Nutrição","ano":"2013","valor":786124.33},{"funcao":"12 - Educação","subFuncao":"306 - Alimentação E Nutrição","ano":"2014","valor":941989.25},{"funcao":"12 - Educação","subFuncao":"361 - Ensino Fundamental","ano":"2012","valor":10102150.78},{"funcao":"12 - Educação","subFuncao":"361 - Ensino Fundamental","ano":"2013","valor":10826575.92},{"funcao":"12 - Educação","subFuncao":"361 - Ensino Fundamental","ano":"2014","valor":11175065.08},{"funcao":"12 - Educação","subFuncao":"362 - Ensino Médio","ano":"2014","valor":1340},{"funcao":"12 - Educação","subFuncao":"364 - Ensino Superior","ano":"2012","valor":137617.4},{"funcao":"12 - Educação","subFuncao":"364 - Ensino Superior","ano":"2013","valor":60076.78},{"funcao":"12 - Educação","subFuncao":"364 - Ensino Superior","ano":"2014","valor":63037.18},{"funcao":"12 - Educação","subFuncao":"365 - Educação Infantil","ano":"2012","valor":3981945.02},{"funcao":"12 - Educação","subFuncao":"365 - Educação Infantil","ano":"2013","valor":4550521.21},{"funcao":"12 - Educação","subFuncao":"365 - Educação Infantil","ano":"2014","valor":5669881.27},{"funcao":"12 - Educação","subFuncao":"367 - Educação Especial","ano":"2012","valor":171774.37},{"funcao":"12 - Educação","subFuncao":"367 - Educação Especial","ano":"2013","valor":227308.2},{"funcao":"12 - Educação","subFuncao":"367 - Educação Especial","ano":"2014","valor":159827.64},{"funcao":"13 - Cultura","subFuncao":"392 - Difusão Cultural","ano":"2012","valor":544888.19},{"funcao":"13 - Cultura","subFuncao":"392 - Difusão Cultural","ano":"2013","valor":313640.85},{"funcao":"13 - Cultura","subFuncao":"392 - Difusão Cultural","ano":"2014","valor":406194.59},{"funcao":"15 - Urbanismo","subFuncao":"451 - Infra-Estrutura Urbana","ano":"2012","valor":184685.89},{"funcao":"15 - Urbanismo","subFuncao":"451 - Infra-Estrutura Urbana","ano":"2013","valor":235647.92},{"funcao":"15 - Urbanismo","subFuncao":"451 - Infra-Estrutura Urbana","ano":"2014","valor":225147.18},{"funcao":"15 - Urbanismo","subFuncao":"452 - Serviços Urbanos","ano":"2012","valor":4805402.96},{"funcao":"15 - Urbanismo","subFuncao":"452 - Serviços Urbanos","ano":"2013","valor":6037692.62},{"funcao":"15 - Urbanismo","subFuncao":"452 - Serviços Urbanos","ano":"2014","valor":5968724.12},{"funcao":"17 - Saneamento","subFuncao":"512 - Saneamento Básico Urbano","ano":"2012","valor":1621035.5},{"funcao":"17 - Saneamento","subFuncao":"512 - Saneamento Básico Urbano","ano":"2013","valor":1738520.57},{"funcao":"17 - Saneamento","subFuncao":"512 - Saneamento Básico Urbano","ano":"2014","valor":1790997.18},{"funcao":"18 - Gestão Ambiental","subFuncao":"541 - Preservação E Conservação Ambiental","ano":"2012","valor":104175.24},{"funcao":"18 - Gestão Ambiental","subFuncao":"541 - Preservação E Conservação Ambiental","ano":"2013","valor":107454.26},{"funcao":"18 - Gestão Ambiental","subFuncao":"541 - Preservação E Conservação Ambiental","ano":"2014","valor":343426.55},{"funcao":"20 - Agricultura","subFuncao":"511 - Saneamento Básico Rural","ano":"2012","valor":292346.44},{"funcao":"20 - Agricultura","subFuncao":"606 - Extensão Rural","ano":"2012","valor":288441.04},{"funcao":"20 - Agricultura","subFuncao":"606 - Extensão Rural","ano":"2013","valor":350504.64},{"funcao":"20 - Agricultura","subFuncao":"606 - Extensão Rural","ano":"2014","valor":428015.92},{"funcao":"23 - Comércio E Serviços","subFuncao":"691 - Promoção Comercial","ano":"2012","valor":4662.5},{"funcao":"23 - Comércio E Serviços","subFuncao":"691 - Promoção Comercial","ano":"2013","valor":12259.12},{"funcao":"23 - Comércio E Serviços","subFuncao":"691 - Promoção Comercial","ano":"2014","valor":87.69},{"funcao":"23 - Comércio E Serviços","subFuncao":"695 - Turismo","ano":"2012","valor":135152.37},{"funcao":"23 - Comércio E Serviços","subFuncao":"695 - Turismo","ano":"2013","valor":47422.87},{"funcao":"23 - Comércio E Serviços","subFuncao":"695 - Turismo","ano":"2014","valor":90436.52},{"funcao":"26 - Transporte","subFuncao":"782 - Transporte Rodoviário","ano":"2012","valor":2896322.83},{"funcao":"26 - Transporte","subFuncao":"782 - Transporte Rodoviário","ano":"2013","valor":1437691.81},{"funcao":"26 - Transporte","subFuncao":"782 - Transporte Rodoviário","ano":"2014","valor":1383076.85},{"funcao":"27 - Desporto E Lazer","subFuncao":"812 - Desporto Comunitário","ano":"2012","valor":707648.65},{"funcao":"27 - Desporto E Lazer","subFuncao":"812 - Desporto Comunitário","ano":"2013","valor":1501219.09},{"funcao":"27 - Desporto E Lazer","subFuncao":"812 - Desporto Comunitário","ano":"2014","valor":917512.3},{"funcao":"28 - Encargos Especiais","subFuncao":"846 - Outros Encargos Especiais","ano":"2012","valor":2168233.15},{"funcao":"28 - Encargos Especiais","subFuncao":"846 - Outros Encargos Especiais","ano":"2013","valor":2557553.38},{"funcao":"28 - Encargos Especiais","subFuncao":"846 - Outros Encargos Especiais","ano":"2014","valor":3134103.33},{"funcao":"01 - Legislativa","subFuncao":"031 - Ação Legislativa","ano":"2012","valor":674491.79},{"funcao":"01 - Legislativa","subFuncao":"031 - Ação Legislativa","ano":"2013","valor":849101.94},{"funcao":"01 - Legislativa","subFuncao":"031 - Ação Legislativa","ano":"2014","valor":898696.55},{"funcao":"04 - Administração","subFuncao":"122 - Administração Geral","ano":"2012","valor":6729617.69},{"funcao":"04 - Administração","subFuncao":"122 - Administração Geral","ano":"2013","valor":6236422.41},{"funcao":"04 - Administração","subFuncao":"122 - Administração Geral","ano":"2014","valor":8466721.49},{"funcao":"08 - Assistência Social","subFuncao":"241 - Assistência Ao Idoso","ano":"2013","valor":405}]