[{"funcao":"28 - Encargos Especiais","subFuncao":"841 - Refinanciamento Da Dívida Interna","ano":"2012","valor":242045.02},{"funcao":"28 - Encargos Especiais","subFuncao":"841 - Refinanciamento Da Dívida Interna","ano":"2013","valor":276735.48},{"funcao":"08 - Assistência Social","subFuncao":"244 - Assistência Comunitária","ano":"2012","valor":621417.62},{"funcao":"08 - Assistência Social","subFuncao":"244 - Assistência Comunitária","ano":"2013","valor":733222.44},{"funcao":"08 - Assistência Social","subFuncao":"244 - Assistência Comunitária","ano":"2014","valor":863146.01},{"funcao":"10 - Saúde","subFuncao":"301 - Atenção Básica","ano":"2012","valor":6934480.83},{"funcao":"10 - Saúde","subFuncao":"301 - Atenção Básica","ano":"2013","valor":7622437.83},{"funcao":"10 - Saúde","subFuncao":"301 - Atenção Básica","ano":"2014","valor":9327493.38},{"funcao":"10 - Saúde","subFuncao":"302 - Assistência Hospitalar E Ambulatorial","ano":"2014","valor":26685.31},{"funcao":"27 - Desporto E Lazer","subFuncao":"812 - Desporto Comunitário","ano":"2012","valor":465106.53},{"funcao":"27 - Desporto E Lazer","subFuncao":"812 - Desporto Comunitário","ano":"2013","valor":403216.01},{"funcao":"27 - Desporto E Lazer","subFuncao":"812 - Desporto Comunitário","ano":"2014","valor":365846.76},{"funcao":"12 - Educação","subFuncao":"365 - Educação Infantil","ano":"2012","valor":1388437.12},{"funcao":"12 - Educação","subFuncao":"365 - Educação Infantil","ano":"2013","valor":1459667.68},{"funcao":"12 - Educação","subFuncao":"365 - Educação Infantil","ano":"2014","valor":1712430.55},{"funcao":"12 - Educação","subFuncao":"364 - Ensino Superior","ano":"2012","valor":758138.5},{"funcao":"12 - Educação","subFuncao":"364 - Ensino Superior","ano":"2013","valor":591014.5},{"funcao":"12 - Educação","subFuncao":"364 - Ensino Superior","ano":"2014","valor":690678.91},{"funcao":"12 - Educação","subFuncao":"361 - Ensino Fundamental","ano":"2012","valor":6095176.36},{"funcao":"12 - Educação","subFuncao":"361 - Ensino Fundamental","ano":"2013","valor":7441432.73},{"funcao":"12 - Educação","subFuncao":"361 - Ensino Fundamental","ano":"2014","valor":8229005.82},{"funcao":"12 - Educação","subFuncao":"306 - Alimentação E Nutrição","ano":"2012","valor":618118.29},{"funcao":"12 - Educação","subFuncao":"306 - Alimentação E Nutrição","ano":"2013","valor":655310.93},{"funcao":"12 - Educação","subFuncao":"306 - Alimentação E Nutrição","ano":"2014","valor":719861.09},{"funcao":"10 - Saúde","subFuncao":"304 - Vigilância Sanitária","ano":"2012","valor":162692.2},{"funcao":"10 - Saúde","subFuncao":"304 - Vigilância Sanitária","ano":"2013","valor":382518.26},{"funcao":"08 - Assistência Social","subFuncao":"243 - Assistência À Criança E Ao Adoslescente","ano":"2012","valor":34883.39},{"funcao":"08 - Assistência Social","subFuncao":"243 - Assistência À Criança E Ao Adoslescente","ano":"2013","valor":19029.27},{"funcao":"08 - Assistência Social","subFuncao":"243 - Assistência À Criança E Ao Adoslescente","ano":"2014","valor":450.02},{"funcao":"04 - Administração","subFuncao":"846 - Outros Encargos Especiais","ano":"2014","valor":543456.21},{"funcao":"04 - Administração","subFuncao":"843 - Serviço Da Dívida Interna","ano":"2014","valor":109887.84},{"funcao":"04 - Administração","subFuncao":"123 - Administração Financeira","ano":"2014","valor":2436907.06},{"funcao":"04 - Administração","subFuncao":"122 - Administração Geral","ano":"2012","valor":3471210.53},{"funcao":"04 - Administração","subFuncao":"122 - Administração Geral","ano":"2013","valor":3824046.58},{"funcao":"04 - Administração","subFuncao":"122 - Administração Geral","ano":"2014","valor":1966023.44},{"funcao":"01 - Legislativa","subFuncao":"031 - Ação Legislativa","ano":"2012","valor":862923.96},{"funcao":"01 - Legislativa","subFuncao":"031 - Ação Legislativa","ano":"2013","valor":1016131.08},{"funcao":"01 - Legislativa","subFuncao":"031 - Ação Legislativa","ano":"2014","valor":1280517.51},{"funcao":"26 - Transporte","subFuncao":"782 - Transporte Rodoviário","ano":"2012","valor":1788388.68},{"funcao":"26 - Transporte","subFuncao":"782 - Transporte Rodoviário","ano":"2013","valor":1862575.38},{"funcao":"26 - Transporte","subFuncao":"782 - Transporte Rodoviário","ano":"2014","valor":1846884.45},{"funcao":"23 - Comércio E Serviços","subFuncao":"691 - Promoção Comercial","ano":"2013","valor":490},{"funcao":"20 - Agricultura","subFuncao":"606 - Extensão Rural","ano":"2012","valor":475997.26},{"funcao":"20 - Agricultura","subFuncao":"606 - Extensão Rural","ano":"2013","valor":218102.99},{"funcao":"20 - Agricultura","subFuncao":"606 - Extensão Rural","ano":"2014","valor":286396.8},{"funcao":"16 - Habitação","subFuncao":"482 - Habitação Urbana","ano":"2013","valor":540000},{"funcao":"15 - Urbanismo","subFuncao":"452 - Serviços Urbanos","ano":"2012","valor":2057281.97},{"funcao":"15 - Urbanismo","subFuncao":"452 - Serviços Urbanos","ano":"2013","valor":2011870.04},{"funcao":"15 - Urbanismo","subFuncao":"452 - Serviços Urbanos","ano":"2014","valor":1542735.85},{"funcao":"15 - Urbanismo","subFuncao":"451 - Infra-Estrutura Urbana","ano":"2012","valor":1505375.56},{"funcao":"15 - Urbanismo","subFuncao":"451 - Infra-Estrutura Urbana","ano":"2013","valor":341272.72},{"funcao":"15 - Urbanismo","subFuncao":"451 - Infra-Estrutura Urbana","ano":"2014","valor":609092.61},{"funcao":"13 - Cultura","subFuncao":"392 - Difusão Cultural","ano":"2012","valor":471809.5},{"funcao":"13 - Cultura","subFuncao":"392 - Difusão Cultural","ano":"2013","valor":686246.14},{"funcao":"13 - Cultura","subFuncao":"392 - Difusão Cultural","ano":"2014","valor":691398.42},{"funcao":"28 - Encargos Especiais","subFuncao":"846 - Outros Encargos Especiais","ano":"2014","valor":308491.46}]